isi_sdk_8_0/__init__.py
isi_sdk_8_0/api_client.py
isi_sdk_8_0/configuration.py
isi_sdk_8_0/rest.py
isi_sdk_8_0/api/__init__.py
isi_sdk_8_0/api/antivirus_api.py
isi_sdk_8_0/api/audit_api.py
isi_sdk_8_0/api/auth_api.py
isi_sdk_8_0/api/auth_groups_api.py
isi_sdk_8_0/api/auth_providers_api.py
isi_sdk_8_0/api/auth_roles_api.py
isi_sdk_8_0/api/auth_users_api.py
isi_sdk_8_0/api/cloud_api.py
isi_sdk_8_0/api/cluster_api.py
isi_sdk_8_0/api/cluster_nodes_api.py
isi_sdk_8_0/api/debug_api.py
isi_sdk_8_0/api/dedupe_api.py
isi_sdk_8_0/api/event_api.py
isi_sdk_8_0/api/file_filter_api.py
isi_sdk_8_0/api/filepool_api.py
isi_sdk_8_0/api/filesystem_api.py
isi_sdk_8_0/api/fsa_api.py
isi_sdk_8_0/api/fsa_results_api.py
isi_sdk_8_0/api/hardening_api.py
isi_sdk_8_0/api/hardware_api.py
isi_sdk_8_0/api/job_api.py
isi_sdk_8_0/api/license_api.py
isi_sdk_8_0/api/local_api.py
isi_sdk_8_0/api/namespace_api.py
isi_sdk_8_0/api/network_api.py
isi_sdk_8_0/api/network_groupnets_api.py
isi_sdk_8_0/api/network_groupnets_subnets_api.py
isi_sdk_8_0/api/protocols_api.py
isi_sdk_8_0/api/protocols_hdfs_api.py
isi_sdk_8_0/api/quota_api.py
isi_sdk_8_0/api/quota_quotas_api.py
isi_sdk_8_0/api/quota_reports_api.py
isi_sdk_8_0/api/remotesupport_api.py
isi_sdk_8_0/api/snapshot_api.py
isi_sdk_8_0/api/snapshot_changelists_api.py
isi_sdk_8_0/api/snapshot_snapshots_api.py
isi_sdk_8_0/api/statistics_api.py
isi_sdk_8_0/api/storagepool_api.py
isi_sdk_8_0/api/sync_api.py
isi_sdk_8_0/api/sync_policies_api.py
isi_sdk_8_0/api/sync_reports_api.py
isi_sdk_8_0/api/sync_target_api.py
isi_sdk_8_0/api/upgrade_api.py
isi_sdk_8_0/api/upgrade_cluster_api.py
isi_sdk_8_0/api/worm_api.py
isi_sdk_8_0/api/zones_api.py
isi_sdk_8_0/api/zones_summary_api.py
isi_sdk_8_0/models/__init__.py
isi_sdk_8_0/models/access_point_create_params.py
isi_sdk_8_0/models/acl_object.py
isi_sdk_8_0/models/ads_provider_controllers.py
isi_sdk_8_0/models/ads_provider_controllers_controller.py
isi_sdk_8_0-0.2.11.dist-info/DESCRIPTION.rst
isi_sdk_8_0-0.2.11.dist-info/METADATA
isi_sdk_8_0-0.2.11.dist-info/RECORD
isi_sdk_8_0-0.2.11.dist-info/WHEEL
isi_sdk_8_0-0.2.11.dist-info/metadata.json
isi_sdk_8_0-0.2.11.dist-info/top_level.txt
